[
    {
        "market": "Misaş",
        "urun_adi": "Max Frıgola 65ml",
        "resim_linki": "https://misassanalmarket.com/218413-home_default/max-frigola-65ml.jpg",
        "urun_fiyati": "₺20,00"
    },
    {
        "market": "Misaş",
        "urun_adi": "Algıda Combo Kakao-Vanilya 60ml",
        "resim_linki": "https://misassanalmarket.com/218377-home_default/algida-combo-kakao-vanilya-60ml.jpg",
        "urun_fiyati": "₺7,50"
    },
    {
        "market": "Misaş",
        "urun_adi": "Max Twıster Ocean 65ml",
        "resim_linki": "https://misassanalmarket.com/218339-home_default/max-twister-ocean-65ml.jpg",
        "urun_fiyati": "₺10,00"
    },
    {
        "market": "Misaş",
        "urun_adi": "Algıda Combo Çilek-Vanilya 60ml",
        "resim_linki": "https://misassanalmarket.com/218376-home_default/algida-combo-cilek-vanilya-60ml.jpg",
        "urun_fiyati": "₺7,50"
    },
    {
        "market": "Misaş",
        "urun_adi": "Kahraman Efendi Sade 610Ml",
        "resim_linki": "https://misassanalmarket.com/218363-home_default/kahraman-efendi-sade-610ml.jpg",
        "urun_fiyati": "₺44,90"
    },
    {
        "market": "Misaş",
        "urun_adi": "Max Twıster Forest 65ml",
        "resim_linki": "https://misassanalmarket.com/218340-home_default/max-twister-forest-65ml.jpg",
        "urun_fiyati": "₺10,00"
    },
    {
        "market": "Misaş",
        "urun_adi": "Magnum Classıc 100 ml",
        "resim_linki": "https://misassanalmarket.com/218432-home_default/magnum-classic-100-ml.jpg",
        "urun_fiyati": "₺45,00"
    },
    {
        "market": "Misaş",
        "urun_adi": "Algıda Classıcs Kakao 65ml",
        "resim_linki": "https://misassanalmarket.com/218438-home_default/algida-classics-kakao-65ml.jpg",
        "urun_fiyati": "₺15,00"
    },
    {
        "market": "Misaş",
        "urun_adi": "Algıda Classıcs Vanilya 65ml",
        "resim_linki": "https://misassanalmarket.com/218342-home_default/algida-classics-vanilya-65ml.jpg",
        "urun_fiyati": "₺15,00"
    },
    {
        "market": "Misaş",
        "urun_adi": "Algida Keyif Vanilya 750ml",
        "resim_linki": "https://misassanalmarket.com/218446-home_default/algida-keyif-vanilya-750ml.jpg",
        "urun_fiyati": "₺59,90"
    },
    {
        "market": "Misaş",
        "urun_adi": "Erpiliç Tab. Piliç Döner Dondurulmuş",
        "resim_linki": "https://misassanalmarket.com/218001-home_default/erpilic-tab-pilic-doner-dondurulmus.jpg",
        "urun_fiyati": "₺109,95"
    },
    {
        "market": "Misaş",
        "urun_adi": "Algıda Classıcs Antep Fıstık 65ml",
        "resim_linki": "https://misassanalmarket.com/218437-home_default/algida-classics-antep-fistik-65ml.jpg",
        "urun_fiyati": "₺15,00"
    },
    {
        "market": "Misaş",
        "urun_adi": "Magnum Beya 100 ml",
        "resim_linki": "https://misassanalmarket.com/218431-home_default/magnum-beya-100-ml.jpg",
        "urun_fiyati": "₺45,00"
    },
    {
        "market": "Misaş",
        "urun_adi": "Algida Dövme Büyük 1400 Gr",
        "resim_linki": "https://misassanalmarket.com/218381-home_default/algida-dovme-buyuk-1400-gr.jpg",
        "urun_fiyati": "₺84,90"
    },
    {
        "market": "Misaş",
        "urun_adi": "Cornetto Classıco Cikolota 125ml",
        "resim_linki": "https://misassanalmarket.com/218328-home_default/cornetto-classico-cikolota-125ml.jpg",
        "urun_fiyati": "₺30,00"
    },
    {
        "market": "Misaş",
        "urun_adi": "Algida Keyif Fıstık Vanilya Kakao Cl 1400Ml",
        "resim_linki": "https://misassanalmarket.com/218361-home_default/algida-keyif-fistik-vanilya-kakao-cl-1400ml.jpg",
        "urun_fiyati": "₺79,90"
    },
    {
        "market": "Misaş",
        "urun_adi": "Magnum Mini Core Rfa (Klasik-Badem-Beyaz) 360 Ml",
        "resim_linki": "https://misassanalmarket.com/218325-home_default/magnum-mini-core-rfa-klasik-badem-beyaz-360-ml.jpg",
        "urun_fiyati": "₺169,90"
    },
    {
        "market": "Misaş",
        "urun_adi": "Algida Twister Tub 750Ml",
        "resim_linki": "https://misassanalmarket.com/218407-home_default/algida-twister-tub-750ml.jpg",
        "urun_fiyati": "₺64,90"
    },
    {
        "market": "Misaş",
        "urun_adi": "Cornetto Classıco Kaymak 125ml",
        "resim_linki": "https://misassanalmarket.com/218327-home_default/cornetto-classico-kaymak-125ml.jpg",
        "urun_fiyati": "₺30,00"
    },
    {
        "market": "Misaş",
        "urun_adi": "Magnum Mini Cookie&Badem 345ml",
        "resim_linki": "https://misassanalmarket.com/218429-home_default/magnum-mini-cookie-badem-345ml.jpg",
        "urun_fiyati": "₺169,90"
    },
    {
        "market": "Misaş",
        "urun_adi": "Cartedor Nd.Sel.Çikolatalı Karn. 800 Ml",
        "resim_linki": "https://misassanalmarket.com/218386-home_default/cartedor-ndselcikolatali-karn-800-ml.jpg",
        "urun_fiyati": "₺149,90"
    },
    {
        "market": "Misaş",
        "urun_adi": "Magnum Mini Clasıc 345ml",
        "resim_linki": "https://misassanalmarket.com/218358-home_default/magnum-mini-clasic-345ml.jpg",
        "urun_fiyati": "₺169,90"
    },
    {
        "market": "Misaş",
        "urun_adi": "Pınar Milfoy Hamuru 500gr",
        "resim_linki": "https://misassanalmarket.com/219436-home_default/pinar-milfoy-hamuru-500gr.jpg",
        "urun_fiyati": "₺49,95"
    },
    {
        "market": "Misaş",
        "urun_adi": "Magnum Mp. Classic Promo 4*360 Ml",
        "resim_linki": "https://misassanalmarket.com/218353-home_default/magnum-mp-classic-promo-4360-ml.jpg",
        "urun_fiyati": "₺169,90"
    },
    {
        "market": "Misaş",
        "urun_adi": "Max Twister Mini Multi Pack 400Ml",
        "resim_linki": "https://misassanalmarket.com/218393-home_default/max-twister-mini-multi-pack-400ml.jpg",
        "urun_fiyati": "₺74,90"
    },
    {
        "market": "Misaş",
        "urun_adi": "Pınar Milföy Hamuru 1000gr",
        "resim_linki": "https://misassanalmarket.com/219437-home_default/pinar-milfoy-hamuru-1000gr.jpg",
        "urun_fiyati": "₺89,95"
    },
    {
        "market": "Misaş",
        "urun_adi": "Algida Keyif Vişne Limon 750 ml",
        "resim_linki": "https://misassanalmarket.com/218445-home_default/algida-keyif-visne-limon-750-ml.jpg",
        "urun_fiyati": "₺59,90"
    },
    {
        "market": "Misaş",
        "urun_adi": "Viennetta Vanilya Çikolata 800ml",
        "resim_linki": "https://misassanalmarket.com/218443-home_default/viennetta-vanilya-cikolata-800ml.jpg",
        "urun_fiyati": "₺119,90"
    },
    {
        "market": "Misaş",
        "urun_adi": "Pınar Ucgen Mantı 400 gr",
        "resim_linki": "https://misassanalmarket.com/219429-home_default/pinar-ucgen-manti-400-gr.jpg",
        "urun_fiyati": "₺76,95"
    },
    {
        "market": "Misaş",
        "urun_adi": "Algıda Keyif Choc-Van 110ml",
        "resim_linki": "https://misassanalmarket.com/218384-home_default/algida-keyif-choc-van-110ml.jpg",
        "urun_fiyati": "₺15,00"
    },
    {
        "market": "Misaş",
        "urun_adi": "Süperfresh Patates 450 gr",
        "resim_linki": "https://misassanalmarket.com/219270-home_default/superfresh-patates-450-gr.jpg",
        "urun_fiyati": "₺93,75"
    },
    {
        "market": "Misaş",
        "urun_adi": "Magnum Double Çikolata 100Ml",
        "resim_linki": "https://misassanalmarket.com/218450-home_default/magnum-double-cikolata-100ml.jpg",
        "urun_fiyati": "₺45,00"
    },
    {
        "market": "Misaş",
        "urun_adi": "Pınar Bohca Mantı 400 gr",
        "resim_linki": "https://misassanalmarket.com/219430-home_default/pinar-bohca-manti-400-gr.jpg",
        "urun_fiyati": "₺76,95"
    },
    {
        "market": "Misaş",
        "urun_adi": "Magnum Mini Badem 345ml",
        "resim_linki": "https://misassanalmarket.com/218354-home_default/magnum-mini-badem-345ml.jpg",
        "urun_fiyati": "₺169,90"
    },
    {
        "market": "Misaş",
        "urun_adi": "Erpiliç Tab. Piliç Şinitzel Dondurulmuş",
        "resim_linki": "https://misassanalmarket.com/217999-home_default/erpilic-tab-pilic-sinitzel-dondurulmus.jpg",
        "urun_fiyati": "₺59,95"
    },
    {
        "market": "Misaş",
        "urun_adi": "Max Gökkuşağı 59ml",
        "resim_linki": "https://misassanalmarket.com/218335-home_default/max-gokkusagi-59ml.jpg",
        "urun_fiyati": "₺7,50"
    },
    {
        "market": "Misaş",
        "urun_adi": "Magnum Bademli 100 ml.",
        "resim_linki": "https://misassanalmarket.com/218433-home_default/magnum-bademli-100-ml.jpg",
        "urun_fiyati": "₺45,00"
    },
    {
        "market": "Misaş",
        "urun_adi": "Algida Maraş Sade Çifte Dövülmüş 500gr",
        "resim_linki": "https://misassanalmarket.com/218436-home_default/algida-maras-sade-cifte-dovulmus-500gr.jpg",
        "urun_fiyati": "₺119,90"
    },
    {
        "market": "Misaş",
        "urun_adi": "Algıda Keyif Kakao-Vanilya 750ml",
        "resim_linki": "https://misassanalmarket.com/218444-home_default/algida-keyif-kakao-vanilya-750ml.jpg",
        "urun_fiyati": "₺59,90"
    },
    {
        "market": "Misaş",
        "urun_adi": "Algida Classic Oreo Stick 65Ml",
        "resim_linki": "https://misassanalmarket.com/218398-home_default/algida-classic-oreo-stick-65ml.jpg",
        "urun_fiyati": "₺15,00"
    },
    {
        "market": "Misaş",
        "urun_adi": "Süperfresh Kayseri Mantı 400 gr",
        "resim_linki": "https://misassanalmarket.com/219269-home_default/superfresh-kayseri-manti-400-gr.jpg",
        "urun_fiyati": "₺64,95"
    },
    {
        "market": "Misaş",
        "urun_adi": "Süperfresh Milfoy Hamuru 500 gr",
        "resim_linki": "https://misassanalmarket.com/219264-home_default/superfresh-milfoy-hamuru-500-gr.jpg",
        "urun_fiyati": "₺49,95"
    },
    {
        "market": "Misaş",
        "urun_adi": "Süperfresh Milfoy Hamuru 1000 gr",
        "resim_linki": "https://misassanalmarket.com/219261-home_default/superfresh-milfoy-hamuru-1000-gr.jpg",
        "urun_fiyati": "₺84,95"
    },
    {
        "market": "Misaş",
        "urun_adi": "Algida Maraş Cl Mandıra 500 Ml",
        "resim_linki": "https://misassanalmarket.com/218362-home_default/algida-maras-cl-mandira-500-ml.jpg",
        "urun_fiyati": "₺119,90"
    },
    {
        "market": "Misaş",
        "urun_adi": "Süper Fresh Patates Parmak1000 gr",
        "resim_linki": "https://misassanalmarket.com/219271-home_default/super-fresh-patates-parmak1000-gr.jpg",
        "urun_fiyati": "₺134,95"
    },
    {
        "market": "Misaş",
        "urun_adi": "Magnum Karadut 360 ml.",
        "resim_linki": "https://misassanalmarket.com/218440-home_default/magnum-karadut-360-ml.jpg",
        "urun_fiyati": "₺169,90"
    },
    {
        "market": "Misaş",
        "urun_adi": "Cartedor Nd Sel Meyve Sol. 800 Ml",
        "resim_linki": "https://misassanalmarket.com/218385-home_default/cartedor-nd-sel-meyve-sol-800-ml.jpg",
        "urun_fiyati": "₺149,90"
    },
    {
        "market": "Misaş",
        "urun_adi": "Magnum Double Karadut 100Ml",
        "resim_linki": "https://misassanalmarket.com/218359-home_default/magnum-double-karadut-100ml.jpg",
        "urun_fiyati": "₺45,00"
    },
    {
        "market": "Misaş",
        "urun_adi": "Algida Maraş Kesme 650ml",
        "resim_linki": "https://misassanalmarket.com/218380-home_default/algida-maras-kesme-650ml.jpg",
        "urun_fiyati": "₺119,90"
    },
    {
        "market": "Misaş",
        "urun_adi": "Algida Keyif A.Fistık Vanilya 750ml",
        "resim_linki": "https://misassanalmarket.com/218447-home_default/algida-keyif-afistik-vanilya-750ml.jpg",
        "urun_fiyati": "₺59,90"
    },
    {
        "market": "Misaş",
        "urun_adi": "Algida Maraş Sade Keçi Sütlü 500 ml",
        "resim_linki": "https://misassanalmarket.com/218364-home_default/algida-maras-sade-keci-sutlu-500-ml.jpg",
        "urun_fiyati": "₺109,90"
    },
    {
        "market": "Misaş",
        "urun_adi": "Pınar İnegöl Köfte 390R",
        "resim_linki": "https://misassanalmarket.com/219431-home_default/pinar-inegol-kofte-390r.jpg",
        "urun_fiyati": "₺299,95"
    },
    {
        "market": "Misaş",
        "urun_adi": "Max Twıster Island 65ml",
        "resim_linki": "https://misassanalmarket.com/218341-home_default/max-twister-island-65ml.jpg",
        "urun_fiyati": "₺10,00"
    },
    {
        "market": "Misaş",
        "urun_adi": "Süperfresh Pizza King 780 gr",
        "resim_linki": "https://misassanalmarket.com/219266-home_default/superfresh-pizza-king-780-gr.jpg",
        "urun_fiyati": "₺189,95"
    },
    {
        "market": "Misaş",
        "urun_adi": "Pınar Piliç Kroket Eko 430gr",
        "resim_linki": "https://misassanalmarket.com/219434-home_default/pinar-pilic-kroket-eko-430gr.jpg",
        "urun_fiyati": "₺159,95"
    },
    {
        "market": "Misaş",
        "urun_adi": "Erpiliç Tab.Piliç Nugget Dondurulmuş",
        "resim_linki": "https://misassanalmarket.com/218000-home_default/erpilic-tabpilic-nugget-dondurulmus.jpg",
        "urun_fiyati": "₺59,95"
    },
    {
        "market": "Misaş",
        "urun_adi": "Erpiliç Tab. Piliç  Köfte Dondurulmuş",
        "resim_linki": "https://misassanalmarket.com/217998-home_default/erpilic-tab-pilic-kofte-dondurulmus.jpg",
        "urun_fiyati": "₺56,95"
    },
    {
        "market": "a101",
        "urun_adi": "Superfresh Dondurulmuş Çubuk Patates 1000 G",
        "resim_linki": "https://cdn2.a101.com.tr/dbmk89vnr/CALL/Image/get/boW4zwo6TH_256x256.png",
        "urun_fiyati": "₺125,00"
    },
    {
        "market": "a101",
        "urun_adi": "Nimet Dondurulmuş Patates 1000 G",
        "resim_linki": "https://cdn2.a101.com.tr/dbmk89vnr/CALL/Image/get/K-2IvySAtH_256x256.png",
        "urun_fiyati": "₺55,00"
    },
    {
        "market": "a101",
        "urun_adi": "Nimet Patlıcanlı Rulo Börek 500 G",
        "resim_linki": "https://cdn2.a101.com.tr/dbmk89vnr/CALL/Image/get/nx3sedhOaT_256x256.png",
        "urun_fiyati": "₺60,00"
    },
    {
        "market": "a101",
        "urun_adi": "Nimet Patatesli Rulo Börek 500 G",
        "resim_linki": "https://cdn2.a101.com.tr/dbmk89vnr/CALL/Image/get/CTYqMHDmEX_256x256.png",
        "urun_fiyati": "₺60,00"
    },
    {
        "market": "a101",
        "urun_adi": "Nimet Ispanaklı Peynirli Mini Rulo Börek 500 G",
        "resim_linki": "https://cdn2.a101.com.tr/dbmk89vnr/CALL/Image/get/ams2VydEbW_256x256.png",
        "urun_fiyati": "₺60,00"
    },
    {
        "market": "a101",
        "urun_adi": "Nimet Dondurulmuş Milföy Hamuru 1000 G",
        "resim_linki": "https://cdn2.a101.com.tr/dbmk89vnr/CALL/Image/get/iMaAxePETG_256x256.png",
        "urun_fiyati": "₺49,75"
    },
    {
        "market": "a101",
        "urun_adi": "Nimet Dondurulmuş Pizza 4x205 G",
        "resim_linki": "https://cdn2.a101.com.tr/dbmk89vnr/CALL/Image/get/-uz0OikqaV_256x256.png",
        "urun_fiyati": "₺82,50"
    },
    {
        "market": "a101",
        "urun_adi": "Superfresh Dondurulmuş Tavuk Dürüm Tost 180 G",
        "resim_linki": "https://cdn2.a101.com.tr/dbmk89vnr/CALL/Image/get/qvqRvOr3rN_256x256.png",
        "urun_fiyati": "₺55,00"
    },
    {
        "market": "a101",
        "urun_adi": "Çokça Dondurulmuş Mısır 450 G",
        "resim_linki": "https://cdn2.a101.com.tr/dbmk89vnr/CALL/Image/get/0bJ7ToS8tf_256x256.png",
        "urun_fiyati": "₺42,50"
    },
    {
        "market": "a101",
        "urun_adi": "Dr. Oetker Pizza 4'lü 676 G",
        "resim_linki": "https://cdn2.a101.com.tr/dbmk89vnr/CALL/Image/get/f1zQgV94jN_256x256.png",
        "urun_fiyati": "₺179,95"
    },
    {
        "market": "a101",
        "urun_adi": "Çokça Dondurulmuş Bezelye 450 G",
        "resim_linki": "https://cdn2.a101.com.tr/dbmk89vnr/CALL/Image/get/vmqBwBNfA5_256x256.png",
        "urun_fiyati": "₺32,00"
    },
    {
        "market": "a101",
        "urun_adi": "Çokça Dondurulmuş Bamya 450 G",
        "resim_linki": "https://cdn2.a101.com.tr/dbmk89vnr/CALL/Image/get/PHYqzappjq_256x256.png",
        "urun_fiyati": "₺65,00"
    },
    {
        "market": "a101",
        "urun_adi": "Beşler Mantı 350 G",
        "resim_linki": "https://cdn2.a101.com.tr/dbmk89vnr/CALL/Image/get/07RPKZzlBl_256x256.png",
        "urun_fiyati": "₺49,00"
    },
    {
        "market": "a101",
        "urun_adi": "Nimet Dondurulmuş Soyalı Mantı 450 G",
        "resim_linki": "https://cdn2.a101.com.tr/dbmk89vnr/CALL/Image/get/IRC-RDxQ2l_256x256.png",
        "urun_fiyati": "₺26,50"
    },
    {
        "market": "a101",
        "urun_adi": "Dr. Oetker Guseppe Dondurulmuş Karışık Pizza 405 G",
        "resim_linki": "https://cdn2.a101.com.tr/dbmk89vnr/CALL/Image/get/M-8IxKK41B_256x256.png",
        "urun_fiyati": "₺99,00"
    },
    {
        "market": "a101",
        "urun_adi": "Sinangil Çeşidim Dondurulmuş Simit 4x100 G",
        "resim_linki": "https://cdn2.a101.com.tr/dbmk89vnr/CALL/Image/get/rM1ewTgonb_256x256.png",
        "urun_fiyati": "₺54,90"
    },
    {
        "market": "a101",
        "urun_adi": "Superfresh Dondurulmuş Pizza King 600 G",
        "resim_linki": "https://cdn2.a101.com.tr/dbmk89vnr/CALL/Image/get/IICyhi5TE9_256x256.png",
        "urun_fiyati": "₺109,00"
    },
    {
        "market": "a101",
        "urun_adi": "Nimet Dondurulmuş Ispanaklı Tepsi Böreği 800 G",
        "resim_linki": "https://cdn2.a101.com.tr/dbmk89vnr/CALL/Image/get/qF6BSdxnSC_256x256.png",
        "urun_fiyati": "₺80,00"
    },
    {
        "market": "a101",
        "urun_adi": "Nimet Dondurulmuş Peynirli Tepsi Börek 800 G",
        "resim_linki": "https://cdn2.a101.com.tr/dbmk89vnr/CALL/Image/get/JaSCtj0Mx5_256x256.png",
        "urun_fiyati": "₺80,00"
    },
    {
        "market": "a101",
        "urun_adi": "Nimet Dondurulmuş Su Böreği 800 G",
        "resim_linki": "https://cdn2.a101.com.tr/dbmk89vnr/CALL/Image/get/Z9fs8sVqB-_256x256.png",
        "urun_fiyati": "₺115,00"
    },
    {
        "market": "a101",
        "urun_adi": "Nimet Dondurulmuş Kalem Böreği 400 G",
        "resim_linki": "https://cdn2.a101.com.tr/dbmk89vnr/CALL/Image/get/Hp64L5rVJv_256x256.png",
        "urun_fiyati": "₺34,50"
    },
    {
        "market": "a101",
        "urun_adi": "Nimet Dondurulmuş Boyoz 6x60 G",
        "resim_linki": "https://cdn2.a101.com.tr/dbmk89vnr/CALL/Image/get/as7HasXNgP_256x256.png",
        "urun_fiyati": "₺45,00"
    },
    {
        "market": "a101",
        "urun_adi": "Nimet Dondurulmuş Soğan Halkası 450 G",
        "resim_linki": "https://cdn2.a101.com.tr/dbmk89vnr/CALL/Image/get/B40ZT7HUrt_256x256.png",
        "urun_fiyati": "₺32,50"
    },
    {
        "market": "a101",
        "urun_adi": "Feast Churros Dondurulmuş Patates 1000 G",
        "resim_linki": "https://cdn2.a101.com.tr/dbmk89vnr/CALL/Image/get/MxEAOAc34G_256x256.png",
        "urun_fiyati": "₺125,00"
    },
    {
        "market": "a101",
        "urun_adi": "Ponti Dondurulmuş Balkan Çöreği 500 G",
        "resim_linki": "https://cdn2.a101.com.tr/dbmk89vnr/CALL/Image/get/3PHgMY8z-Y_256x256.png",
        "urun_fiyati": "₺65,00"
    },
    {
        "market": "a101",
        "urun_adi": "Çokça Konserve Hindi Fileto 120 G",
        "resim_linki": "https://cdn2.a101.com.tr/dbmk89vnr/CALL/Image/get/59i4kBViBL_256x256.png",
        "urun_fiyati": "₺55,00"
    },
    {
        "market": "a101",
        "urun_adi": "Çokça Konserve Hindi Tandır 120 G",
        "resim_linki": "https://cdn2.a101.com.tr/dbmk89vnr/CALL/Image/get/jnXa4Xni01_256x256.png",
        "urun_fiyati": "₺55,00"
    },
    {
        "market": "a101",
        "urun_adi": "Yayla Barbunya Pilaki 400 G",
        "resim_linki": "https://cdn2.a101.com.tr/dbmk89vnr/CALL/Image/get/Gn226Hkz4E_256x256.png",
        "urun_fiyati": "₺44,90"
    },
    {
        "market": "a101",
        "urun_adi": "Çokça Barbunya Pilaki 400 G",
        "resim_linki": "https://cdn2.a101.com.tr/dbmk89vnr/CALL/Image/get/PyEv6vp9Uw_256x256.png",
        "urun_fiyati": "₺32,50"
    },
    {
        "market": "a101",
        "urun_adi": "Yurt Kuru Fasulye 400 G",
        "resim_linki": "https://cdn2.a101.com.tr/dbmk89vnr/CALL/Image/get/kazQNgClYP_256x256.png",
        "urun_fiyati": "₺42,90"
    },
    {
        "market": "a101",
        "urun_adi": "Çokça Meze Çiğ Köfte 384 G",
        "resim_linki": "https://cdn2.a101.com.tr/dbmk89vnr/CALL/Image/get/UX4BKKU77x_256x256.png",
        "urun_fiyati": "₺25,50"
    },
    {
        "market": "a101",
        "urun_adi": "Meze Turko Rus Salatası 250 G",
        "resim_linki": "https://cdn2.a101.com.tr/dbmk89vnr/CALL/Image/get/efBLwRy3ci_256x256.png",
        "urun_fiyati": "₺22,50"
    },
    {
        "market": "a101",
        "urun_adi": "Çokça Meze Çiğköfte Dürüm 260 G",
        "resim_linki": "https://cdn2.a101.com.tr/dbmk89vnr/CALL/Image/get/KeD9Jk6A4e_256x256.png",
        "urun_fiyati": "₺24,50"
    },
    {
        "market": "a101",
        "urun_adi": "Dardanel Mr. No Kaşarlı Salamlı veya Bol Peynirli Sandviç 130 G",
        "resim_linki": "https://cdn2.a101.com.tr/dbmk89vnr/CALL/Image/get/6q85Ekne89_256x256.png",
        "urun_fiyati": "₺27,50"
    },
    {
        "market": "a101",
        "urun_adi": "Sinangil Soğuk Baklava 400 G",
        "resim_linki": "https://cdn2.a101.com.tr/dbmk89vnr/CALL/Image/get/U96eP2tWln_256x256.png",
        "urun_fiyati": "₺149,00"
    },
    {
        "market": "a101",
        "urun_adi": "Kekspır Dondurulmuş Çikolatalı Sufle 2x100 G",
        "resim_linki": "https://cdn2.a101.com.tr/dbmk89vnr/CALL/Image/get/vX86PwHgmh_256x256.png",
        "urun_fiyati": "₺50,00"
    },
    {
        "market": "a101",
        "urun_adi": "Sam Dondurulmuş Künefe 135 G",
        "resim_linki": "https://cdn2.a101.com.tr/dbmk89vnr/CALL/Image/get/5r1vn8ncd2_256x256.png",
        "urun_fiyati": "₺21,25"
    },
    {
        "market": "a101",
        "urun_adi": "Özsüt Sefer Usta Dondurulmuş Çikolatalı Pasta 650 G",
        "resim_linki": "https://cdn2.a101.com.tr/dbmk89vnr/CALL/Image/get/pm0gbofScG_256x256.png",
        "urun_fiyati": "₺120,00"
    },
    {
        "market": "a101",
        "urun_adi": "Coquette Dondurulmuş Limonlu Cheesecake 650 G",
        "resim_linki": "https://cdn2.a101.com.tr/dbmk89vnr/CALL/Image/get/vH64u8q-Xl_256x256.png",
        "urun_fiyati": "₺129,00"
    },
    {
        "market": "a101",
        "urun_adi": "Coquette Dondurulmuş Frambuazlı Cheesecake 650 G ",
        "resim_linki": "https://cdn2.a101.com.tr/dbmk89vnr/CALL/Image/get/2KKqlXmwCW_256x256.png",
        "urun_fiyati": "₺129,00"
    },
    {
        "market": "a101",
        "urun_adi": "Sam Dondurulmuş Kakaolu Muska Katmer 200 G",
        "resim_linki": "https://cdn2.a101.com.tr/dbmk89vnr/CALL/Image/get/07-K0pum-8_256x256.png",
        "urun_fiyati": "₺82,00"
    },
    {
        "market": "a101",
        "urun_adi": "Algida Twister Forest Dondurma 65 Ml",
        "resim_linki": "https://cdn2.a101.com.tr/dbmk89vnr/CALL/Image/get/PZftgeIiqb_256x256.png",
        "urun_fiyati": "₺10,00"
    },
    {
        "market": "a101",
        "urun_adi": "Algida Classics Kakao Dondurma 65 Ml",
        "resim_linki": "https://cdn2.a101.com.tr/dbmk89vnr/CALL/Image/get/5Dl-rxgLUv_256x256.png",
        "urun_fiyati": "₺15,00"
    },
    {
        "market": "a101",
        "urun_adi": "Algida Classics Vanilya Dondurma 65 Ml",
        "resim_linki": "https://cdn2.a101.com.tr/dbmk89vnr/CALL/Image/get/q4u4ELQR1E_256x256.png",
        "urun_fiyati": "₺15,00"
    },
    {
        "market": "a101",
        "urun_adi": "Algida Classics Oreo Dondurma 65 Ml",
        "resim_linki": "https://cdn2.a101.com.tr/dbmk89vnr/CALL/Image/get/SG1RpSHDJG_256x256.png",
        "urun_fiyati": "₺15,00"
    },
    {
        "market": "a101",
        "urun_adi": "Algida Magnum Double Çikolata Dondurma 95 Ml",
        "resim_linki": "https://cdn2.a101.com.tr/dbmk89vnr/CALL/Image/get/-IPy9XboAs_256x256.png",
        "urun_fiyati": "₺45,00"
    },
    {
        "market": "a101",
        "urun_adi": "Algida Keyif Kornet Çikolata/Vanilya Dondurma 110 Ml",
        "resim_linki": "https://cdn2.a101.com.tr/dbmk89vnr/CALL/Image/get/NXeQOEszmT_256x256.png",
        "urun_fiyati": "₺15,00"
    },
    {
        "market": "a101",
        "urun_adi": "Algida Cornetto Classico Çilekli Kaymaklı Dondurma 120 Ml",
        "resim_linki": "https://cdn2.a101.com.tr/dbmk89vnr/CALL/Image/get/-pt1OCxtli_256x256.png",
        "urun_fiyati": "₺30,00"
    },
    {
        "market": "a101",
        "urun_adi": "Algida Cornetto Disc Choco Coffee Dondurma 130 Ml",
        "resim_linki": "https://cdn2.a101.com.tr/dbmk89vnr/CALL/Image/get/KY0QygkF3j_256x256.png",
        "urun_fiyati": "₺40,00"
    },
    {
        "market": "a101",
        "urun_adi": "Algida Nugger Kaymaklı Çikolatalı Dondurma 145 Ml",
        "resim_linki": "https://cdn2.a101.com.tr/dbmk89vnr/CALL/Image/get/zE3nDnl25U_256x256.png",
        "urun_fiyati": "₺35,00"
    },
    {
        "market": "a101",
        "urun_adi": "Algida Nogger Kakao Karamel Dondurma 145 Ml",
        "resim_linki": "https://cdn2.a101.com.tr/dbmk89vnr/CALL/Image/get/N8OK9fUt8o_256x256.png",
        "urun_fiyati": "₺35,00"
    },
    {
        "market": "a101",
        "urun_adi": "Algida Viennetta Çikolatalı Vanilyalı Dondurma 90 Ml",
        "resim_linki": "https://cdn2.a101.com.tr/dbmk89vnr/CALL/Image/get/wPMfN4pAsl_256x256.png",
        "urun_fiyati": "₺15,00"
    },
    {
        "market": "a101",
        "urun_adi": "Algida Magnum Bademli Dondurma 100 Ml",
        "resim_linki": "https://cdn2.a101.com.tr/dbmk89vnr/CALL/Image/get/Po7kg1tms3_256x256.png",
        "urun_fiyati": "₺45,00"
    },
    {
        "market": "a101",
        "urun_adi": "Algida Cornetto Classico Kaymak Dondurma 125 Ml",
        "resim_linki": "https://cdn2.a101.com.tr/dbmk89vnr/CALL/Image/get/Q6RmK-XJ-m_256x256.png",
        "urun_fiyati": "₺30,00"
    },
    {
        "market": "a101",
        "urun_adi": "Algida Magnum Double Karadut/Böğürtlen Dondurma 95 Ml",
        "resim_linki": "https://cdn2.a101.com.tr/dbmk89vnr/CALL/Image/get/is9IKZFbfZ_256x256.png",
        "urun_fiyati": "₺45,00"
    },
    {
        "market": "a101",
        "urun_adi": "Algida Boom Boom Dondurma 80 Ml ",
        "resim_linki": "https://cdn2.a101.com.tr/dbmk89vnr/CALL/Image/get/gDQw0ffCsD_256x256.png",
        "urun_fiyati": "₺25,00"
    },
    {
        "market": "a101",
        "urun_adi": "Algida Frigola Dondurma 60 Ml ",
        "resim_linki": "https://cdn2.a101.com.tr/dbmk89vnr/CALL/Image/get/mAKAlFBGyV_256x256.png",
        "urun_fiyati": "₺20,00"
    },
    {
        "market": "a101",
        "urun_adi": "Algida Cornetto Oreo Disc Dondurma 130 Ml",
        "resim_linki": "https://cdn2.a101.com.tr/dbmk89vnr/CALL/Image/get/8hXkhbL-WD_256x256.png",
        "urun_fiyati": "₺40,00"
    },
    {
        "market": "a101",
        "urun_adi": "Algida Cornetto Disc Milka Dondurma 130 Ml",
        "resim_linki": "https://cdn2.a101.com.tr/dbmk89vnr/CALL/Image/get/MbN9aWI6QL_256x256.png",
        "urun_fiyati": "₺40,00"
    },
    {
        "market": "a101",
        "urun_adi": "Algida Magnum Beyaz Dondurma 100 Ml",
        "resim_linki": "https://cdn2.a101.com.tr/dbmk89vnr/CALL/Image/get/mzrpti9VZn_256x256.png",
        "urun_fiyati": "₺45,00"
    },
    {
        "market": "a101",
        "urun_adi": "Algida Disc Cornetto Vanilya Karamel Dondurma 130 Ml",
        "resim_linki": "https://cdn2.a101.com.tr/dbmk89vnr/CALL/Image/get/IXolr94np4_256x256.png",
        "urun_fiyati": "₺40,00"
    },
    {
        "market": "a101",
        "urun_adi": "Algida Conboo Kakao/Vanilya Dondurma 60 Ml",
        "resim_linki": "https://cdn2.a101.com.tr/dbmk89vnr/CALL/Image/get/PC5ewO3A7G_256x256.png",
        "urun_fiyati": "₺7,50"
    },
    {
        "market": "a101",
        "urun_adi": "Algida Conboo Çilek/Vanilya Dondurma 60 Ml",
        "resim_linki": "https://cdn2.a101.com.tr/dbmk89vnr/CALL/Image/get/kRbcilFg51_256x256.png",
        "urun_fiyati": "₺7,50"
    },
    {
        "market": "a101",
        "urun_adi": "Algida Max Minimilk Kakao Dondurma 35 Ml",
        "resim_linki": "https://cdn2.a101.com.tr/dbmk89vnr/CALL/Image/get/Ljoi24Rjn8_256x256.png",
        "urun_fiyati": "₺5,00"
    },
    {
        "market": "a101",
        "urun_adi": "Xroll Kağıt Helva 45 G",
        "resim_linki": "https://cdn2.a101.com.tr/dbmk89vnr/CALL/Image/get/2Ml10rXE3f_256x256.png",
        "urun_fiyati": "₺10,00"
    },
    {
        "market": "a101",
        "urun_adi": "Algida Magnum Mini Badem Dondurma 6x57,5 Ml",
        "resim_linki": "https://cdn2.a101.com.tr/dbmk89vnr/CALL/Image/get/o14SLf1jt6_256x256.png",
        "urun_fiyati": "₺169,90"
    },
    {
        "market": "a101",
        "urun_adi": "Algida Boncremo Kakao/Vanilya/Çilek Dondurma 1400 Ml",
        "resim_linki": "https://cdn2.a101.com.tr/dbmk89vnr/CALL/Image/get/oOjOOniCVC_256x256.png",
        "urun_fiyati": "₺64,90"
    },
    {
        "market": "a101",
        "urun_adi": "Algida Boncremo Kakao/Vanilya/Fıstık Dondurma 1400 Ml",
        "resim_linki": "https://cdn2.a101.com.tr/dbmk89vnr/CALL/Image/get/KT42TFQTvE_256x256.png",
        "urun_fiyati": "₺64,90"
    },
    {
        "market": "a101",
        "urun_adi": "Algida Boncremo Kakao Vanilya Dondurma 1400 Ml",
        "resim_linki": "https://cdn2.a101.com.tr/dbmk89vnr/CALL/Image/get/Y5LDithvoJ_256x256.png",
        "urun_fiyati": "₺64,90"
    },
    {
        "market": "a101",
        "urun_adi": "Algida Dövme Dondurma 1400 Ml",
        "resim_linki": "https://cdn2.a101.com.tr/dbmk89vnr/CALL/Image/get/okKFNQLU8W_256x256.png",
        "urun_fiyati": "₺84,90"
    },
    {
        "market": "a101",
        "urun_adi": "Algida Magnum Mini Classic/Badem/Beyaz Dondurma 6x57,5 Ml",
        "resim_linki": "https://cdn2.a101.com.tr/dbmk89vnr/CALL/Image/get/Q7VogwuHZM_256x256.png",
        "urun_fiyati": "₺169,90"
    },
    {
        "market": "a101",
        "urun_adi": "Algida Magnum Mini Double Çikolata/Karadut/Karamel/Böğürtlen 6x60 Ml",
        "resim_linki": "https://cdn2.a101.com.tr/dbmk89vnr/CALL/Image/get/VfQR1x-Xoh_256x256.png",
        "urun_fiyati": "₺169,90"
    },
    {
        "market": "a101",
        "urun_adi": "Algida Carte D'or İsviçre Çikolata/Karamel/Muz Dondurma 850 Ml",
        "resim_linki": "https://cdn2.a101.com.tr/dbmk89vnr/CALL/Image/get/BpcPCDeibf_256x256.png",
        "urun_fiyati": "₺139,90"
    },
    {
        "market": "a101",
        "urun_adi": "Algida Carte D'or Vişne/Bitter/Vanilya Dondurma 850 Ml",
        "resim_linki": "https://cdn2.a101.com.tr/dbmk89vnr/CALL/Image/get/NYwm0cNDvG_256x256.png",
        "urun_fiyati": "₺139,90"
    },
    {
        "market": "a101",
        "urun_adi": "Algida Carte D'or Bal Badem/Karamel/Vanilya Dondurma 850 Ml",
        "resim_linki": "https://cdn2.a101.com.tr/dbmk89vnr/CALL/Image/get/07AZDCjhrT_256x256.png",
        "urun_fiyati": "₺139,90"
    },
    {
        "market": "a101",
        "urun_adi": "Algida Magnum Mini Classic Dondurma 6x57,5 Ml",
        "resim_linki": "https://cdn2.a101.com.tr/dbmk89vnr/CALL/Image/get/WdFgQq6GI7_256x256.png",
        "urun_fiyati": "₺169,90"
    },
    {
        "market": "a101",
        "urun_adi": "Algida Magnum Mini Euphoria Bademli Dondurma 353 Ml",
        "resim_linki": "https://cdn2.a101.com.tr/dbmk89vnr/CALL/Image/get/itBxtdQedo_256x256.png",
        "urun_fiyati": "₺169,90"
    },
    {
        "market": "a101",
        "urun_adi": "Algida Magnum Mini Cookie Dondurma 6x57,5 Ml ",
        "resim_linki": "https://cdn2.a101.com.tr/dbmk89vnr/CALL/Image/get/tZIo4JjuUE_256x256.png",
        "urun_fiyati": "₺169,90"
    },
    {
        "market": "a101",
        "urun_adi": "Freedo Dolce Mini Badem Dondurma 6x60 Ml",
        "resim_linki": "https://cdn2.a101.com.tr/dbmk89vnr/CALL/Image/get/BHXNkOt1lo_256x256.png",
        "urun_fiyati": "₺109,00"
    },
    {
        "market": "a101",
        "urun_adi": "Freedo Dolce Mini Classic/Badem/Beyaz Dondurma 6x60 Ml",
        "resim_linki": "https://cdn2.a101.com.tr/dbmk89vnr/CALL/Image/get/PNfqgwDCxb_256x256.png",
        "urun_fiyati": "₺109,00"
    },
    {
        "market": "a101",
        "urun_adi": "Freedo Dolce Mini Classic/Badem/Karadut Dondurma 6x60 Ml",
        "resim_linki": "https://cdn2.a101.com.tr/dbmk89vnr/CALL/Image/get/hu9zipvWYR_256x256.png",
        "urun_fiyati": "₺109,00"
    },
    {
        "market": "a101",
        "urun_adi": "Algida Carte D'or Patisserie Dondurma 800 Ml",
        "resim_linki": "https://cdn2.a101.com.tr/dbmk89vnr/CALL/Image/get/2FeSh8JupM_256x256.png",
        "urun_fiyati": "₺149,90"
    },
    {
        "market": "a101",
        "urun_adi": "Algida Kadayıflı Fındıklı Maraş Dondurma 500 Ml",
        "resim_linki": "https://cdn2.a101.com.tr/dbmk89vnr/CALL/Image/get/gqHGt0Lt-i_256x256.png",
        "urun_fiyati": "₺119,90"
    },
    {
        "market": "a101",
        "urun_adi": "Algida Keyif Vişne Limon Dondurma 750 Ml",
        "resim_linki": "https://cdn2.a101.com.tr/dbmk89vnr/CALL/Image/get/vXQjyHyrJr_256x256.png",
        "urun_fiyati": "₺59,90"
    },
    {
        "market": "a101",
        "urun_adi": "Algida Maraş Çifte Dövülmüş Dondurma 500 Ml",
        "resim_linki": "https://cdn2.a101.com.tr/dbmk89vnr/CALL/Image/get/7oa70Zo3av_256x256.png",
        "urun_fiyati": "₺119,90"
    },
    {
        "market": "a101",
        "urun_adi": "Algida Maraş Sade Dondurma 500 Ml",
        "resim_linki": "https://cdn2.a101.com.tr/dbmk89vnr/CALL/Image/get/9j4zpEPnvU_256x256.png",
        "urun_fiyati": "₺109,90"
    },
    {
        "market": "a101",
        "urun_adi": "Algida Carte D'or Selection Çikolata Karnavalı Dondurma 800 Ml",
        "resim_linki": "https://cdn2.a101.com.tr/dbmk89vnr/CALL/Image/get/ukHYgBT8qv_256x256.png",
        "urun_fiyati": "₺149,90"
    },
    {
        "market": "a101",
        "urun_adi": "Algida Keyif Kakao Vanilya Dondurma 750 Ml",
        "resim_linki": "https://cdn2.a101.com.tr/dbmk89vnr/CALL/Image/get/qBVNInzptt_256x256.png",
        "urun_fiyati": "₺59,90"
    },
    {
        "market": "a101",
        "urun_adi": "Algida Twister Mini Dondurma 8x50 Ml",
        "resim_linki": "https://cdn2.a101.com.tr/dbmk89vnr/CALL/Image/get/VBNa8oyT0w_256x256.png",
        "urun_fiyati": "₺74,90"
    },
    {
        "market": "a101",
        "urun_adi": "Algida Vienetta Çikolata/Vanilya Dondurma 800 Ml",
        "resim_linki": "https://cdn2.a101.com.tr/dbmk89vnr/CALL/Image/get/r50uAXbrN7_256x256.png",
        "urun_fiyati": "₺119,90"
    },
    {
        "market": "a101",
        "urun_adi": "Algida Carte D'or Selection Meyve Şöleni Dondurma 800 Ml",
        "resim_linki": "https://cdn2.a101.com.tr/dbmk89vnr/CALL/Image/get/wDFTqY94nO_256x256.png",
        "urun_fiyati": "₺149,90"
    },
    {
        "market": "a101",
        "urun_adi": "Algida Keyif Vanilya Dondurma 750 Ml",
        "resim_linki": "https://cdn2.a101.com.tr/dbmk89vnr/CALL/Image/get/5NzZyfSSoX_256x256.png",
        "urun_fiyati": "₺59,90"
    },
    {
        "market": "a101",
        "urun_adi": "Algida Maraş Sade Çikolata Dondurma 500 Ml",
        "resim_linki": "https://cdn2.a101.com.tr/dbmk89vnr/CALL/Image/get/oIFXaFGPH-_256x256.png",
        "urun_fiyati": "₺109,90"
    },
    {
        "market": "a101",
        "urun_adi": "Algida Keyif Kakao Vanilya Dondurma 1800 Ml ",
        "resim_linki": "https://cdn2.a101.com.tr/dbmk89vnr/CALL/Image/get/DoWXkxmt4k_256x256.png",
        "urun_fiyati": "₺109,90"
    },
    {
        "market": "a101",
        "urun_adi": "Algida Keyif Fıstık/Vanilya Dondurma 750 Ml",
        "resim_linki": "https://cdn2.a101.com.tr/dbmk89vnr/CALL/Image/get/hxaPVhwsW6_256x256.png",
        "urun_fiyati": "₺59,90"
    },
    {
        "market": "a101",
        "urun_adi": "Freedo Vini Vanilyalı Kakaolu Dondurma 1000 Ml",
        "resim_linki": "https://cdn2.a101.com.tr/dbmk89vnr/CALL/Image/get/ItC8sDTLPe_256x256.png",
        "urun_fiyati": "₺47,50"
    },
    {
        "market": "a101",
        "urun_adi": "Freedo Vini Vişne Çilek Dondurma Dondurma 1500 Ml",
        "resim_linki": "https://cdn2.a101.com.tr/dbmk89vnr/CALL/Image/get/-jPnYayHhh_256x256.png",
        "urun_fiyati": "₺59,50"
    },
    {
        "market": "a101",
        "urun_adi": "Freedo Vini Kakao/Çilek/Vanilya Dondurma 1500 Ml",
        "resim_linki": "https://cdn2.a101.com.tr/dbmk89vnr/CALL/Image/get/Pe2mhCYYD4_256x256.png",
        "urun_fiyati": "₺59,50"
    },
    {
        "market": "a101",
        "urun_adi": "Freedo Vini Gold Kaymaklı Dondurma 1000 Ml",
        "resim_linki": "https://cdn2.a101.com.tr/dbmk89vnr/CALL/Image/get/hcp9M4a7MH_256x256.png",
        "urun_fiyati": "₺95,00"
    },
    {
        "market": "a101",
        "urun_adi": "Freedo Vini Vanilya Dondurma 1000 Ml",
        "resim_linki": "https://cdn2.a101.com.tr/dbmk89vnr/CALL/Image/get/NbB2PW8Oen_256x256.png",
        "urun_fiyati": "₺47,50"
    },
    {
        "market": "migros",
        "urun_adi": "Magnum Mini Double Çikolata, Karadut & Böğürtlen, Karamel (6'lı)",
        "urun_fiyati": "169,90 TL",
        "resim_linki": "https://images.migrosone.com/sanalmarket/product/11578275/11578275-653500.jpg"
    },
    {
        "market": "migros",
        "urun_adi": "Magnum Mini Classic, Badem, Beyaz 345 Ml 6'lı",
        "urun_fiyati": "169,90 TL",
        "resim_linki": "https://images.migrosone.com/sanalmarket/product/11578701/11578701-0a7e58.jpg"
    },
    {
        "market": "migros",
        "urun_adi": "Magnum Mini Double Euphorıa Limon Ahududu Badem 353 ML",
        "urun_fiyati": "169,90 TL",
        "resim_linki": "https://images.migrosone.com/sanalmarket/product/11570055/11570055-224dd5.jpg"
    },
    {
        "market": "migros",
        "urun_adi": "Magnum Mini Badem 6'lı 345 Ml",
        "urun_fiyati": "169,90 TL",
        "resim_linki": "https://images.migrosone.com/sanalmarket/product/11578702/11578702-dc92ed.jpg"
    },
    {
        "market": "migros",
        "urun_adi": "Magnum Mini Cookie & Badem 345 Ml",
        "urun_fiyati": "169,90 TL",
        "resim_linki": "https://images.migrosone.com/sanalmarket/product/11578749/11578749-0dd8fd.jpg"
    },
    {
        "market": "migros",
        "urun_adi": "Magnum Euphoria Limon Ahududu 85 Ml",
        "urun_fiyati": "45,00 TL",
        "resim_linki": "https://images.migrosone.com/sanalmarket/product/11570047/11570047-7218b4.jpg"
    },
    {
        "market": "migros",
        "urun_adi": "Algida Nogger Sandwich Çikolata Karamel 145 ml",
        "urun_fiyati": "35,00 TL",
        "resim_linki": "https://images.migrosone.com/sanalmarket/product/11575910/11575910-bc5916.jpg"
    },
    {
        "market": "migros",
        "urun_adi": "Algida Max Gökkuşağı 59 Ml",
        "urun_fiyati": "7,50 TL",
        "resim_linki": "https://images.migrosone.com/sanalmarket/product/11578759/11578759-99b3be.jpg"
    },
    {
        "market": "migros",
        "urun_adi": "Magnum Mini Classic 345 Ml 6'lı",
        "urun_fiyati": "169,90 TL",
        "resim_linki": "https://images.migrosone.com/sanalmarket/product/11578704/11578704-69100c.jpg"
    },
    {
        "market": "migros",
        "urun_adi": "Cornetto Disc Vanilya Karamel 130Ml",
        "urun_fiyati": "40,00 TL",
        "resim_linki": "https://images.migrosone.com/sanalmarket/product/11578989/11578989-6ebeed.jpg"
    },
    {
        "market": "migros",
        "urun_adi": "Algida Boom Boom 80 Ml",
        "urun_fiyati": "25,00 TL",
        "resim_linki": "https://images.migrosone.com/sanalmarket/product/11570074/11570074-f3790e.jpg"
    },
    {
        "market": "migros",
        "urun_adi": "Algida Conboo Çilek Vanilya 60 Ml",
        "urun_fiyati": "7,50 TL",
        "resim_linki": "https://images.migrosone.com/sanalmarket/product/11578938/11578938-c95913.jpg"
    },
    {
        "market": "migros",
        "urun_adi": "Carte d'Or Bal Badem Vanilya Karamel 850 ml",
        "urun_fiyati": "139,90 TL",
        "resim_linki": "https://images.migrosone.com/sanalmarket/product/11578925/11578925-1661a6.jpg"
    },
    {
        "market": "migros",
        "urun_adi": "Algida Conboo Kakao Vanilya 60 Ml",
        "urun_fiyati": "7,50 TL",
        "resim_linki": "https://images.migrosone.com/sanalmarket/product/11578939/11578939-9f6636.jpg"
    },
    {
        "market": "migros",
        "urun_adi": "Algida Boom Boom Gold 80 Ml",
        "urun_fiyati": "25,00 TL",
        "resim_linki": "https://images.migrosone.com/sanalmarket/product/11578982/11578982-ad6c1e.jpg"
    },
    {
        "market": "migros",
        "urun_adi": "Golf Maraşım Çikolata - Sade 500 Ml",
        "urun_fiyati": "137,90 TL",
        "resim_linki": "https://images.migrosone.com/sanalmarket/product/11578320/11578320-9112a0.jpg"
    },
    {
        "market": "migros",
        "urun_adi": "Carte d'Or Barista Americano - Latte - Madagaskar Vanilya 850 Ml",
        "urun_fiyati": "139,90 TL",
        "resim_linki": "https://images.migrosone.com/sanalmarket/product/11578974/11578974-ba9fee.jpg"
    },
    {
        "market": "migros",
        "urun_adi": "Golf Sizin İçin Çilek - Kakao - Vanilya 1400 Ml",
        "urun_fiyati": "84,90 TL",
        "resim_linki": "https://images.migrosone.com/sanalmarket/product/11578721/11578721-82a839.jpg"
    },
    {
        "market": "migros",
        "urun_adi": "Snickers 53 Ml",
        "urun_fiyati": "50,00 TL",
        "resim_linki": "https://images.migrosone.com/sanalmarket/product/11578762/11578762-5055ed.jpg"
    },
    {
        "market": "migros",
        "urun_adi": "Bounty 50 Ml",
        "urun_fiyati": "50,00 TL",
        "resim_linki": "https://images.migrosone.com/sanalmarket/product/11578765/11578765-74e372.jpg"
    },
    {
        "market": "migros",
        "urun_adi": "Golf Bravo Crazy Nutty 90ml",
        "urun_fiyati": "50,00 TL",
        "resim_linki": "https://images.migrosone.com/sanalmarket/product/11578850/11578850-b41cd5.jpg"
    },
    {
        "market": "migros",
        "urun_adi": "Eti Alaska Frigo Yer Fıstıklı 47 G",
        "urun_fiyati": "32,50 TL",
        "resim_linki": "https://images.migrosone.com/sanalmarket/product/11570090/11570090-de0508.jpg"
    },
    {
        "market": "migros",
        "urun_adi": "Eti Alaska Frigo Bitter Çikolata Bar 60 G",
        "urun_fiyati": "27,50 TL",
        "resim_linki": "https://images.migrosone.com/sanalmarket/product/11578550/11578550-a8cab7.jpg"
    },
    {
        "market": "migros",
        "urun_adi": "Eti Alaska Frigo Karamelli Çikolata Bar 47 G",
        "urun_fiyati": "27,50 TL",
        "resim_linki": "https://images.migrosone.com/sanalmarket/product/11578669/11578669-331742.jpg"
    },
    {
        "market": "migros",
        "urun_adi": "Eti Alaska Frigo Antep Fıstıklı 47 G",
        "urun_fiyati": "37,50 TL",
        "resim_linki": "https://images.migrosone.com/sanalmarket/product/11578623/11578623-02aba4.jpg"
    },
    {
        "market": "migros",
        "urun_adi": "Kechy Gurme Dondurma Çilek 100 Ml",
        "urun_fiyati": "50,00 TL",
        "resim_linki": "https://images.migrosone.com/sanalmarket/product/11574002/11574002-87a0a3.jpg"
    },
    {
        "market": "migros",
        "urun_adi": "Kechy Stevia Fresh Dondurma Çilek Lime Aronya 500 Ml",
        "urun_fiyati": "220,00 TL",
        "resim_linki": "https://images.migrosone.com/sanalmarket/product/11570072/11570072-2b745d.jpeg"
    },
    {
        "market": "migros",
        "urun_adi": "Pandos Sorbet Vişne 235 G",
        "urun_fiyati": "169,95 TL",
        "resim_linki": "https://images.migrosone.com/sanalmarket/product/11571908/11571908-b453c9.jpg"
    },
    {
        "market": "migros",
        "urun_adi": "Kechy Gurme Dondurma Stevia Çikolata 500 Ml",
        "urun_fiyati": "220,00 TL",
        "resim_linki": "https://images.migrosone.com/sanalmarket/product/11570085/11570085-3f321d.jpg"
    },
    {
        "market": "migros",
        "urun_adi": "Kechy Gurme Dondurma Sade 100 Ml",
        "urun_fiyati": "50,00 TL",
        "resim_linki": "https://images.migrosone.com/sanalmarket/product/11574000/11574000-dc1d1b.jpg"
    },
    {
        "market": "migros",
        "urun_adi": "Manjeri Sütlü & Kaymaklı Dondurma 400 Ml",
        "urun_fiyati": "94,95 TL",
        "resim_linki": "https://images.migrosone.com/sanalmarket/product/11578946/11578946-1bdbc5.jpg"
    },
    {
        "market": "migros",
        "urun_adi": "Kechy Gurme Dondurma Çilek 500 Ml",
        "urun_fiyati": "220,00 TL",
        "resim_linki": "https://images.migrosone.com/sanalmarket/product/11574008/11574008-4e0417.jpg"
    },
    {
        "market": "migros",
        "urun_adi": "Maraşım Türk Kahveli Sade 500 Ml",
        "urun_fiyati": "142,90 TL",
        "resim_linki": "https://images.migrosone.com/sanalmarket/product/11570106/11570106-08a106.jpg"
    },
    {
        "market": "migros",
        "urun_adi": "Algida Maraş Usulü Sade Çikolatalı Dondurma 500 Ml",
        "urun_fiyati": "109,90 TL",
        "resim_linki": "https://images.migrosone.com/sanalmarket/product/11578993/11578993-ba1d98.jpg"
    },
    {
        "market": "migros",
        "urun_adi": "Torpat Parmak Patates 1 Kg",
        "urun_fiyati": "59,95 TL",
        "resim_linki": "https://images.migrosone.com/sanalmarket/product/17014683/torpat-parmak-patates-1-kg-909096.jpg"
    },
    {
        "market": "migros",
        "urun_adi": "Namet Pişmiş Döner 250 G",
        "urun_fiyati": "165,95 TL",
        "resim_linki": "https://images.migrosone.com/sanalmarket/product/25509055/25509055-778b65.png"
    },
    {
        "market": "migros",
        "urun_adi": "Banvit Piliç Schnitzel 700 G",
        "urun_fiyati": "119,95 TL",
        "resim_linki": "https://images.migrosone.com/sanalmarket/product/46040054/46040054-ad2f3f.jpg"
    },
    {
        "market": "migros",
        "urun_adi": "Banvit Piliç Nugget 700 G",
        "urun_fiyati": "117,95 TL",
        "resim_linki": "https://images.migrosone.com/sanalmarket/product/46040053/46040053_1-cab8ae.jpg"
    },
    {
        "market": "migros",
        "urun_adi": "Pizza Mi-Go Karışık Dondurulmuş Pizza 545 G",
        "urun_fiyati": "99,95 TL",
        "resim_linki": "https://images.migrosone.com/sanalmarket/product/5060619/5060619-89c102.jpg"
    },
    {
        "market": "migros",
        "urun_adi": "Muti Dondurulmuş Tatlı Mısır 450 G",
        "urun_fiyati": "42,50 TL",
        "resim_linki": "https://images.migrosone.com/sanalmarket/product/17014756/17014756-f9df7b.png"
    },
    {
        "market": "migros",
        "urun_adi": "Feast Taze Fasulye 450 G",
        "urun_fiyati": "93,95 TL",
        "resim_linki": "https://images.migrosone.com/sanalmarket/product/17014700/17014700-6d850d.jpg"
    },
    {
        "market": "migros",
        "urun_adi": "Gedik Piliç Salamlı Cordon Bleu 285G",
        "urun_fiyati": "70,95 TL",
        "resim_linki": "https://images.migrosone.com/sanalmarket/product/13509406/13509406-ea2af9.png"
    },
    {
        "market": "migros",
        "urun_adi": "Dr.Oetker Ristorante Mini Pizza Mista 600 G",
        "urun_fiyati": "179,95 TL",
        "resim_linki": "https://images.migrosone.com/sanalmarket/product/17552500/17552500-c07708.jpg"
    },
    {
        "market": "migros",
        "urun_adi": "Yaprak Sarma Kg (Mz)",
        "urun_fiyati": "495,00 TL",
        "resim_linki": "https://images.migrosone.com/sanalmarket/product/19000767/19000767-8bacf9.jpg"
    },
    {
        "market": "migros",
        "urun_adi": "Arnavut Ciğeri Kg (Mz)",
        "urun_fiyati": "990,00 TL",
        "resim_linki": "https://images.migrosone.com/sanalmarket/product/19000705/19000705-bf61b6.jpg"
    },
    {
        "market": "migros",
        "urun_adi": "Haydari Kg (Mz)",
        "urun_fiyati": "585,00 TL",
        "resim_linki": "https://images.migrosone.com/sanalmarket/product/19000728/19000728-bb1922.jpg"
    },
    {
        "market": "migros",
        "urun_adi": "Muti Dondurulmuş Ispanak 450G",
        "urun_fiyati": "52,95 TL",
        "resim_linki": "https://images.migrosone.com/sanalmarket/product/17014775/17014775-31d504.jpg"
    },
    {
        "market": "migros",
        "urun_adi": "Pek Food Çıtır Patates 1 Kg",
        "urun_fiyati": "169,95 TL",
        "resim_linki": "https://images.migrosone.com/sanalmarket/product/17014765/17014765-94320e.jpg"
    },
    {
        "market": "migros",
        "urun_adi": "Knorr Hazır Çorba Analı Kızlı Çorbası 4 Kişilik 70 G",
        "urun_fiyati": "32,95 TL",
        "resim_linki": "https://images.migrosone.com/sanalmarket/product/05025392/5025392-a36e3b.jpg"
    },
    {
        "market": "migros",
        "urun_adi": "Oreo Cheesecake 160G",
        "urun_fiyati": "249,95 TL",
        "resim_linki": "https://images.migrosone.com/sanalmarket/product/17600002/17600002-98e6fc.jpg"
    },
    {
        "market": "migros",
        "urun_adi": "Kreple Dana Kıymalı Krep 320 G",
        "urun_fiyati": "109,95 TL",
        "resim_linki": "https://images.migrosone.com/sanalmarket/product/17550078/17550078-bd721b.jpg"
    },
    {
        "market": "migros",
        "urun_adi": "Superfresh Meyve Mix 300 G",
        "urun_fiyati": "149,90 TL",
        "resim_linki": "https://images.migrosone.com/sanalmarket/product/17300007/17300007-78f5a2.jpg"
    },
    {
        "market": "migros",
        "urun_adi": "Çiğ Köfte Seti Orta Boy",
        "urun_fiyati": "179,50 TL",
        "resim_linki": "https://images.migrosone.com/sanalmarket/product/19000883/19000883-153efd.jpg"
    },
    {
        "market": "migros",
        "urun_adi": "Nelipide Lahmacun 5 Adet 500 G",
        "urun_fiyati": "192,95 TL",
        "resim_linki": "https://images.migrosone.com/sanalmarket/product/17555682/nelipide-lahmacun-5-adet-500-g-8d9f8a.jpg"
    },
    {
        "market": "migros",
        "urun_adi": "Knorr Bademli Tavuk Çorbası 75 G",
        "urun_fiyati": "32,95 TL",
        "resim_linki": "https://images.migrosone.com/sanalmarket/product/05020154/5020154-fef00a.jpg"
    },
    {
        "market": "migros",
        "urun_adi": "Muti Dondurulmuş Sarımsak 225G",
        "urun_fiyati": "57,95 TL",
        "resim_linki": "https://images.migrosone.com/sanalmarket/product/17014777/17014777-ec9130.jpg"
    },
    {
        "market": "migros",
        "urun_adi": "Tat Fasulye Pilaki 400 G",
        "urun_fiyati": "49,95 TL",
        "resim_linki": "https://images.migrosone.com/sanalmarket/product/09062106/09062106-a5e3e7.jpg"
    },
    {
        "market": "migros",
        "urun_adi": "Tat Zeytinyağlı Fasulye 380 G",
        "urun_fiyati": "69,95 TL",
        "resim_linki": "https://images.migrosone.com/sanalmarket/product/09062109/09062109-179d99.jpg"
    },
    {
        "market": "migros",
        "urun_adi": "Superfresh Patates Kroket 450 G",
        "urun_fiyati": "54,95 TL",
        "resim_linki": "https://images.migrosone.com/sanalmarket/product/17011078/17011078-2dd87a.jpg"
    },
    {
        "market": "migros",
        "urun_adi": "Feast Gurme Churros Kesim Patates 1 Kg",
        "urun_fiyati": "199,95 TL",
        "resim_linki": "https://images.migrosone.com/sanalmarket/product/17014754/17014754-784c60.jpg"
    },
    {
        "market": "migros",
        "urun_adi": "Migros Dana Döner 250 G",
        "urun_fiyati": "115,75 TL",
        "resim_linki": "https://images.migrosone.com/sanalmarket/product/25030308/25030308-c07d2a.jpg"
    },
    {
        "market": "migros",
        "urun_adi": "Superfresh 7/24 Fırından Sade Poğaça 420 G",
        "urun_fiyati": "139,95 TL",
        "resim_linki": "https://images.migrosone.com/sanalmarket/product/17555956/17555956-c2a3e6.jpg"
    },
    {
        "market": "migros",
        "urun_adi": "Şenpiliç Piliç Nugget 300 G",
        "urun_fiyati": "54,95 TL",
        "resim_linki": "https://images.migrosone.com/sanalmarket/product/13509414/13509414-6d790e.jpg"
    },
    {
        "market": "migros",
        "urun_adi": "Mister No Gurme Mozarella Jambon 145 G",
        "urun_fiyati": "149,00 TL",
        "resim_linki": "https://images.migrosone.com/sanalmarket/product/19007961/19007961-b274d1.jpg"
    },
    {
        "market": "migros",
        "urun_adi": "Gurumen Amerikan Salata 200 G",
        "urun_fiyati": "72,95 TL",
        "resim_linki": "https://images.migrosone.com/sanalmarket/product/19009859/19009859-382471.jpg"
    },
    {
        "market": "migros",
        "urun_adi": "Pek Food Pizza Pepperoni 325G",
        "urun_fiyati": "129,95 TL",
        "resim_linki": "https://images.migrosone.com/sanalmarket/product/17555987/17555987-80b145.jpg"
    },
    {
        "market": "migros",
        "urun_adi": "Feast Dondurulmuş Mini Cheesecake 480 G",
        "urun_fiyati": "319,95 TL",
        "resim_linki": "https://images.migrosone.com/sanalmarket/product/17600070/17600070-2d3613.jpg"
    },
    {
        "market": "migros",
        "urun_adi": "Mira Claus Çikolatalı Sufle 2'Li 200 G",
        "urun_fiyati": "89,95 TL",
        "resim_linki": "https://images.migrosone.com/sanalmarket/product/17601017/17601017-a6df0a.JPG"
    },
    {
        "market": "migros",
        "urun_adi": "Milka Çikolatalı Ve Fındıklı Almondy Kek 400 G",
        "urun_fiyati": "369,95 TL",
        "resim_linki": "https://images.migrosone.com/sanalmarket/product/17601001/17601001-0ad1ef.jpg"
    },
    {
        "market": "migros",
        "urun_adi": "Tire Şiş Sucuk 250 G",
        "urun_fiyati": "257,50 TL",
        "resim_linki": "https://images.migrosone.com/sanalmarket/product/25030248/25030248-fc898c.jpg"
    },
    {
        "market": "migros",
        "urun_adi": "Hasek Dolmalık Şırdan 2'li",
        "urun_fiyati": "219,95 TL",
        "resim_linki": "https://images.migrosone.com/sanalmarket/product/25030333/25030333-bc71c5.jpg"
    },
    {
        "market": "migros",
        "urun_adi": "Yurt Kuru Fasulye 400 G",
        "urun_fiyati": "53,95 TL",
        "resim_linki": "https://images.migrosone.com/sanalmarket/product/09020019/09020019-3900ee.jpg"
    },
    {
        "market": "migros",
        "urun_adi": "Tada Yayla Çorbası 250 G",
        "urun_fiyati": "33,95 TL",
        "resim_linki": "https://images.migrosone.com/sanalmarket/product/09025333/09025333-8deb71.jpg"
    },
    {
        "market": "migros",
        "urun_adi": "Superfresh Frambuaz 300 G",
        "urun_fiyati": "212,00 TL",
        "resim_linki": "https://images.migrosone.com/sanalmarket/product/17300019/17300019-be3f47.jpg"
    },
    {
        "market": "migros",
        "urun_adi": "Çerkez Tavuğu Kg (Mz)",
        "urun_fiyati": "678,00 TL",
        "resim_linki": "https://images.migrosone.com/sanalmarket/product/19000716/19000716-390608.jpg"
    },
    {
        "market": "migros",
        "urun_adi": "Çiğ Köfte Dürüm Adet",
        "urun_fiyati": "45,00 TL",
        "resim_linki": "https://images.migrosone.com/sanalmarket/product/19000780/19000780-b42881.jpg"
    },
    {
        "market": "migros",
        "urun_adi": "Patlıcan Salatası Kg (Mz)",
        "urun_fiyati": "585,00 TL",
        "resim_linki": "https://images.migrosone.com/sanalmarket/product/19000754/19000754-306ddd.jpg"
    },
    {
        "market": "migros",
        "urun_adi": "Mücver Kg (Mz)",
        "urun_fiyati": "564,00 TL",
        "resim_linki": "https://images.migrosone.com/sanalmarket/product/19000749/19000749-3fb143.jpg"
    },
    {
        "market": "migros",
        "urun_adi": "İçli Köfte Kg (Mz)",
        "urun_fiyati": "590,00 TL",
        "resim_linki": "https://images.migrosone.com/sanalmarket/product/19000730/19000730-71f1c7.jpg"
    },
    {
        "market": "migros",
        "urun_adi": "Gurvita İlikli Kemik Sulu Mercimek Çorbası 660 Ml",
        "urun_fiyati": "242,95 TL",
        "resim_linki": "https://images.migrosone.com/sanalmarket/product/25030294/25030294-0bcf2c.png"
    },
    {
        "market": "migros",
        "urun_adi": "Superfresh Sivri Bamya 450 G",
        "urun_fiyati": "149,95 TL",
        "resim_linki": "https://images.migrosone.com/sanalmarket/product/17010021/17010021-29921e.jpg"
    },
    {
        "market": "migros",
        "urun_adi": "Knorr Hazır Çorba Düğün 4 Kişilik 72 G",
        "urun_fiyati": "32,95 TL",
        "resim_linki": "https://images.migrosone.com/sanalmarket/product/5025141/5025141-239e2f.jpg"
    },
    {
        "market": "migros",
        "urun_adi": "Knorr Çabuk Çorba Kıtırlı Kremalı Mantar 19 G",
        "urun_fiyati": "12,95 TL",
        "resim_linki": "https://images.migrosone.com/sanalmarket/product/05020118/05020118-41de14.jpg"
    },
    {
        "market": "migros",
        "urun_adi": "Muti Dondurulmuş Enginar Specıal 4'lü 185G",
        "urun_fiyati": "62,95 TL",
        "resim_linki": "https://images.migrosone.com/sanalmarket/product/17014776/17014776-e900b2.jpg"
    },
    {
        "market": "migros",
        "urun_adi": "Mr.No Peynir Salam Baton Sandviç 130 G",
        "urun_fiyati": "27,50 TL",
        "resim_linki": "https://images.migrosone.com/sanalmarket/product/19000661/19000661-6a3d17.jpg"
    },
    {
        "market": "migros",
        "urun_adi": "Başyazıcı Dondurulmuş Kayseri Yağ Mantısı 300 G",
        "urun_fiyati": "242,95 TL",
        "resim_linki": "https://images.migrosone.com/sanalmarket/product/17550032/17550032-db719d.jpg"
    },
    {
        "market": "migros",
        "urun_adi": "Knorr Kremalı Brokoli Çorbası 70 G",
        "urun_fiyati": "20,00 TL",
        "resim_linki": "https://images.migrosone.com/sanalmarket/product/9025337/9025337-bd3b1f.jpg"
    },
    {
        "market": "migros",
        "urun_adi": "Sushida Ton Wrap 120 G",
        "urun_fiyati": "99,00 TL",
        "resim_linki": "https://images.migrosone.com/sanalmarket/product/19000964/19000964-eb813b.jpg"
    },
    {
        "market": "migros",
        "urun_adi": "Tada Ankara Tava 220 G",
        "urun_fiyati": "164,95 TL",
        "resim_linki": "https://images.migrosone.com/sanalmarket/product/09062199/09062199-fa5fee.jpg"
    },
    {
        "market": "migros",
        "urun_adi": "Pınar Rulo Börek Labneli Ispanaklı 500 G",
        "urun_fiyati": "139,95 TL",
        "resim_linki": "https://images.migrosone.com/sanalmarket/product/17555633/17555633-edccc8.jpg"
    },
    {
        "market": "migros",
        "urun_adi": "Zel İlikli Kemik Sulu Kelle Paça Çorbası 480 Ml",
        "urun_fiyati": "154,95 TL",
        "resim_linki": "https://images.migrosone.com/sanalmarket/product/05025363/05025363-77ff8e.jpg"
    },
    {
        "market": "migros",
        "urun_adi": "Yayla Sebzeli Bulgur Pilavı 250 G",
        "urun_fiyati": "43,95 TL",
        "resim_linki": "https://images.migrosone.com/sanalmarket/product/09062262/09062262-cae58c.jpg"
    },
    {
        "market": "migros",
        "urun_adi": "Yayla Bolonez Soslu Makarna 250 G",
        "urun_fiyati": "43,95 TL",
        "resim_linki": "https://images.migrosone.com/sanalmarket/product/09110017/09110017-c9bb4a.JPG"
    },
    {
        "market": "migros",
        "urun_adi": "Yayla Napoliten Soslu Makarna 250 G",
        "urun_fiyati": "41,95 TL",
        "resim_linki": "https://images.migrosone.com/sanalmarket/product/09112121/9112121-705b59.jpg"
    },
    {
        "market": "migros",
        "urun_adi": "Bizim Mutfak Mantar Çorbası 65 G",
        "urun_fiyati": "29,95 TL",
        "resim_linki": "https://images.migrosone.com/sanalmarket/product/05025023/05025023-fa00fd.jpg"
    },
    {
        "market": "migros",
        "urun_adi": "Bizim Mutfak Domates Çorbası 65 G",
        "urun_fiyati": "29,95 TL",
        "resim_linki": "https://images.migrosone.com/sanalmarket/product/05025019/05025019-e06a37.jpg"
    },
    {
        "market": "migros",
        "urun_adi": "Yayla Etli Özbek Pilavı 200 G",
        "urun_fiyati": "76,95 TL",
        "resim_linki": "https://images.migrosone.com/sanalmarket/product/09062260/09062260-6a5ff1.jpg"
    },
    {
        "market": "migros",
        "urun_adi": "Tada Sebzeli Bulgur Pilavı 250 G",
        "urun_fiyati": "47,95 TL",
        "resim_linki": "https://images.migrosone.com/sanalmarket/product/09024391/09024391-b90b52.jpg"
    },
    {
        "market": "migros",
        "urun_adi": "Mr.No Tavuk Dürüm 135 G",
        "urun_fiyati": "75,00 TL",
        "resim_linki": "https://images.migrosone.com/sanalmarket/product/19000526/19000526-a38524.jpg"
    },
    {
        "market": "migros",
        "urun_adi": "Queen's Harvest Küp Avokado 200 G",
        "urun_fiyati": "154,95 TL",
        "resim_linki": "https://images.migrosone.com/sanalmarket/product/17300016/17300016-e95305.jpg"
    },
    {
        "market": "migros",
        "urun_adi": "Queen's Harvest Yeşil Kuşkonmaz 250 G",
        "urun_fiyati": "171,95 TL",
        "resim_linki": "https://images.migrosone.com/sanalmarket/product/17010023/17010023-9b1e5f.jpg"
    },
    {
        "market": "migros",
        "urun_adi": "Körili Mercimek Köfte Kg (Mz)",
        "urun_fiyati": "490,00 TL",
        "resim_linki": "https://images.migrosone.com/sanalmarket/product/19000699/19000699-3f269c.jpg"
    },
    {
        "market": "migros",
        "urun_adi": "Yayla Yemek Hazır Fasulye Pilaki 400 G",
        "urun_fiyati": "46,95 TL",
        "resim_linki": "https://images.migrosone.com/sanalmarket/product/09112123/9112123-8d7d5c.jpg"
    },
    {
        "market": "migros",
        "urun_adi": "Lavi Canlandıran Meyveler 400 G",
        "urun_fiyati": "169,95 TL",
        "resim_linki": "https://images.migrosone.com/sanalmarket/product/17300021/17300021_1-0a2e10.jpg"
    },
    {
        "market": "şok",
        "urun_adi": "İnci Elma Dilim Patates 1 kg",
        "resim_linki": "https://images.ceptesok.com/badge-icons/badges/frozen.png",
        "urun_fiyati": "59,00₺"
    },
    {
        "market": "şok",
        "urun_adi": "Balık Dünyası Türk Somonu 440 g",
        "resim_linki": "https://images.ceptesok.com/badge-icons/badges/frozen.png",
        "urun_fiyati": "85,00₺"
    },
    {
        "market": "şok",
        "urun_adi": "Balık Dünyası Uskumru Fileto 500 g",
        "resim_linki": "https://images.ceptesok.com/badge-icons/badges/frozen.png",
        "urun_fiyati": "100,00₺"
    },
    {
        "market": "şok",
        "urun_adi": "Carte d'Or Classic Vişne Bitter Vanilya 850 ml",
        "resim_linki": "https://images.ceptesok.com/badge-icons/badges/frozen.png",
        "urun_fiyati": "139,90₺"
    },
    {
        "market": "şok",
        "urun_adi": "Carte d'Or Classic Antep Fıstık Bitter Vanilya 850 ml",
        "resim_linki": "https://images.ceptesok.com/badge-icons/badges/frozen.png",
        "urun_fiyati": "139,90₺"
    },
    {
        "market": "şok",
        "urun_adi": "Carte d'Or Selection Karamel Kurabiye 800 ml",
        "resim_linki": "https://images.ceptesok.com/badge-icons/badges/frozen.png",
        "urun_fiyati": "149,90₺"
    },
    {
        "market": "şok",
        "urun_adi": "Carte d'Or Selection Çikolata Karnavalı 800 ml",
        "resim_linki": "https://images.ceptesok.com/badge-icons/badges/frozen.png",
        "urun_fiyati": "149,90₺"
    },
    {
        "market": "şok",
        "urun_adi": "Algida Keyif Çilek Vanilya Kakao 1400 ml",
        "resim_linki": "https://images.ceptesok.com/badge-icons/badges/frozen.png",
        "urun_fiyati": "79,90₺"
    },
    {
        "market": "şok",
        "urun_adi": "Carte d'Or Classic Çikolata Karamel Muz 850 ml",
        "resim_linki": "https://images.ceptesok.com/badge-icons/badges/frozen.png",
        "urun_fiyati": "139,90₺"
    },
    {
        "market": "şok",
        "urun_adi": "Algida Maraş Usulü Bol Kaymaklı 500 Ml",
        "resim_linki": "https://images.ceptesok.com/badge-icons/badges/frozen.png",
        "urun_fiyati": "119,90₺"
    },
    {
        "market": "şok",
        "urun_adi": "Carte d'Or Selection Gold Çikolata 800 ml",
        "resim_linki": "https://images.ceptesok.com/badge-icons/badges/frozen.png",
        "urun_fiyati": "139,90₺"
    },
    {
        "market": "şok",
        "urun_adi": "Golf Royal Gourmet Yaz Ferahlığı 850 ml",
        "resim_linki": "https://images.ceptesok.com/badge-icons/badges/frozen.png",
        "urun_fiyati": "154,90₺"
    },
    {
        "market": "şok",
        "urun_adi": "Golf Royal Gourmet Belçika Çikolatası 850 Ml",
        "resim_linki": "https://images.ceptesok.com/badge-icons/badges/frozen.png",
        "urun_fiyati": "154,90₺"
    },
    {
        "market": "şok",
        "urun_adi": "Magnum Mini Euphoria Limon Ahududu 353 ml",
        "resim_linki": "https://images.ceptesok.com/badge-icons/badges/frozen.png",
        "urun_fiyati": "169,90₺"
    },
    {
        "market": "şok",
        "urun_adi": "Magnum Mini Double 6'lı 360 ml",
        "resim_linki": "https://images.ceptesok.com/badge-icons/badges/frozen.png",
        "urun_fiyati": "169,90₺"
    },
    {
        "market": "şok",
        "urun_adi": "Magnum Mini Badem 6'lı 345 ml",
        "resim_linki": "https://images.ceptesok.com/badge-icons/badges/frozen.png",
        "urun_fiyati": "169,90₺"
    },
    {
        "market": "şok",
        "urun_adi": "Magnum Mini Classic 6'lı 345 ml",
        "resim_linki": "https://images.ceptesok.com/badge-icons/badges/frozen.png",
        "urun_fiyati": "169,90₺"
    },
    {
        "market": "şok",
        "urun_adi": "Golf Bravo Junior Multipack 6'lı",
        "resim_linki": "https://images.ceptesok.com/badge-icons/badges/frozen.png",
        "urun_fiyati": "179,90₺"
    },
    {
        "market": "şok",
        "urun_adi": "Magnum Mini Classic Badem Beyaz 345 ml",
        "resim_linki": "https://images.ceptesok.com/badge-icons/badges/frozen.png",
        "urun_fiyati": "169,90₺"
    },
    {
        "market": "şok",
        "urun_adi": "Mis Gold Antep Fıstığı Badem Tria 360 ml",
        "resim_linki": "https://images.ceptesok.com/badge-icons/badges/frozen.png",
        "urun_fiyati": "109,00₺"
    },
    {
        "market": "şok",
        "urun_adi": "Buzlat Buz Küpü 700 ml",
        "resim_linki": "https://images.ceptesok.com/cdn-cgi/image/width=216,height=216,fit=pad,quality=100,format=webp/product-assets/sub-folder/f461368a-98bb-462f-8699-b99815c83094.png",
        "urun_fiyati": "54,95₺"
    }
]